README.rst
setup.py
labstep/__init__.py
labstep.egg-info/PKG-INFO
labstep.egg-info/SOURCES.txt
labstep.egg-info/dependency_links.txt
labstep.egg-info/not-zip-safe
labstep.egg-info/requires.txt
labstep.egg-info/top_level.txt
labstep/config/export.py
labstep/constants/__init__.py
labstep/constants/unspecified.py
labstep/constants/version.py
labstep/converter/__init__.py
labstep/converter/htmlToProseMirror.py
labstep/entities/apiKey/model.py
labstep/entities/apiKey/repository.py
labstep/entities/autoshare/model.py
labstep/entities/autoshare/repository.py
labstep/entities/chemical/model.py
labstep/entities/chemical/repository.py
labstep/entities/chemicalReaction/model.py
labstep/entities/chemicalReaction/repository.py
labstep/entities/collaborator/model.py
labstep/entities/collaborator/repository.py
labstep/entities/collaboratorRole/model.py
labstep/entities/collaboratorRole/repository.py
labstep/entities/collaboratorRoleRequirement/model.py
labstep/entities/collaboratorRoleRequirement/repository.py
labstep/entities/collection/model.py
labstep/entities/collection/repository.py
labstep/entities/comment/model.py
labstep/entities/comment/repository.py
labstep/entities/customIdentifierSet/model.py
labstep/entities/customIdentifierSet/repository.py
labstep/entities/device/model.py
labstep/entities/device/repository.py
labstep/entities/deviceBooking/model.py
labstep/entities/deviceBooking/repository.py
labstep/entities/deviceCategory/model.py
labstep/entities/deviceCategory/repository.py
labstep/entities/deviceData/model.py
labstep/entities/deviceData/repository.py
labstep/entities/deviceTemplate/model.py
labstep/entities/deviceTemplate/repository.py
labstep/entities/entityImport/model.py
labstep/entities/entityImport/repository.py
labstep/entities/entityState/model.py
labstep/entities/entityState/repository.py
labstep/entities/entityStateWorkflow/model.py
labstep/entities/entityStateWorkflow/repository.py
labstep/entities/experiment/model.py
labstep/entities/experiment/repository.py
labstep/entities/experimentCondition/model.py
labstep/entities/experimentCondition/repository.py
labstep/entities/experimentDataField/model.py
