Metadata-Version: 2.1
Name: labstep
Version: 3.34.0
Summary: Python SDK for working with the Labstep API
Home-page: http://github.com/Labstep/labstepPy
Author: Labstep
Author-email: dev@labstep.com
License: MIT
Requires-Dist: requests
Requires-Dist: python-dotenv
Requires-Dist: beautifulsoup4
Requires-Dist: Deprecated
Requires-Dist: pathvalidate
Requires-Dist: pandas
Requires-Dist: Pillow
